[
  {
    "name": "CBD Chitu V 3.6 3D Printer Controller Board",
    "technology": "FDM",
    "composition": null,
    "price": "$81.90",
    "manufacturer": "3DFilamenta",
    "website": "http://3dfilamenta.com/",
    "color": null,
    "opacity": 1,
    "tags": null,
    "diameter": 1.75,
    "filament_extrusion_to_flow_multiplier": 1,
    "temp_extrude_default": 200,
    "temp_extrude_min": 190,
    "temp_extrude_max": 210,
    "bed_temp": 60,
    "min_nozzle_diameter": null,
    "extruder_fan_speed": 255,
    "bed_material": "blue tape, glass, glue stick",
    "buy_now": "http://3dfilamenta.com/3dfmstore/3d-printer-controllers/24-cbd-chitu-v-36-3d-printer-controller-board.html"
  },
  {
    "name": "SS316L Stainless Steel Powder",
    "technology": "FDM",
    "composition": null,
    "price": "$73.00",
    "manufacturer": "3DFilamenta",
    "website": "http://3dfilamenta.com/",
    "color": null,
    "opacity": 1,
    "tags": null,
    "diameter": 1.75,
    "filament_extrusion_to_flow_multiplier": 1,
    "temp_extrude_default": 200,
    "temp_extrude_min": 190,
    "temp_extrude_max": 210,
    "bed_temp": 60,
    "min_nozzle_diameter": null,
    "extruder_fan_speed": 255,
    "bed_material": "blue tape, glass, glue stick",
    "buy_now": "http://3dfilamenta.com/3dfmstore/metals-powders/25-ss316-stainless-steel-powder.html"
  },
  {
    "name": "CBD Chitu WiFi Module Addon",
    "technology": "FDM",
    "composition": null,
    "price": "$18.00",
    "manufacturer": "3DFilamenta",
    "website": "http://3dfilamenta.com/",
    "color": null,
    "opacity": 1,
    "tags": null,
    "diameter": 1.75,
    "filament_extrusion_to_flow_multiplier": 1,
    "temp_extrude_default": 200,
    "temp_extrude_min": 190,
    "temp_extrude_max": 210,
    "bed_temp": 60,
    "min_nozzle_diameter": null,
    "extruder_fan_speed": 255,
    "bed_material": "blue tape, glass, glue stick",
    "buy_now": "http://3dfilamenta.com/3dfmstore/3d-printer-components/27-cbd-chitu-wifi-module-addon.html"
  },
  {
    "name": "3DFM ABS Filament- Natural",
    "technology": "FDM",
    "composition": null,
    "price": "$19.90",
    "manufacturer": "3DFilamenta",
    "website": "http://3dfilamenta.com/",
    "color": null,
    "opacity": 1,
    "tags": null,
    "diameter": 1.75,
    "filament_extrusion_to_flow_multiplier": 1,
    "temp_extrude_default": 230,
    "temp_extrude_min": 200,
    "temp_extrude_max": 250,
    "bed_temp": 110,
    "min_nozzle_diameter": null,
    "extruder_fan_speed": 0,
    "bed_material": "kapton, abs slurry, acrylic, blue tape",
    "buy_now": "http://3dfilamenta.com/3dfmstore/3d-printer-consumables/35-3dfm-abs-filament-natural.html"
  },
  {
    "name": "3DFM ABS Filament- Yellow",
    "technology": "FDM",
    "composition": null,
    "price": "$19.90",
    "manufacturer": "3DFilamenta",
    "website": "http://3dfilamenta.com/",
    "color": null,
    "opacity": 1,
    "tags": null,
    "diameter": 1.75,
    "filament_extrusion_to_flow_multiplier": 1,
    "temp_extrude_default": 230,
    "temp_extrude_min": 200,
    "temp_extrude_max": 250,
    "bed_temp": 110,
    "min_nozzle_diameter": null,
    "extruder_fan_speed": 0,
    "bed_material": "kapton, abs slurry, acrylic, blue tape",
    "buy_now": "http://3dfilamenta.com/3dfmstore/3d-printer-filaments/37-3dfm-abs-filament-yellow.html"
  },
  {
    "name": "3DFM ABS Filament- Green",
    "technology": "FDM",
    "composition": null,
    "price": "$19.90",
    "manufacturer": "3DFilamenta",
    "website": "http://3dfilamenta.com/",
    "color": null,
    "opacity": 1,
    "tags": null,
    "diameter": 1.75,
    "filament_extrusion_to_flow_multiplier": 1,
    "temp_extrude_default": 230,
    "temp_extrude_min": 200,
    "temp_extrude_max": 250,
    "bed_temp": 110,
    "min_nozzle_diameter": null,
    "extruder_fan_speed": 0,
    "bed_material": "kapton, abs slurry, acrylic, blue tape",
    "buy_now": "http://3dfilamenta.com/3dfmstore/3d-printer-consumables/36-3dfm-abs-filament-green.html"
  },
  {
    "name": "3DFM ABS Filament- Blue",
    "technology": "FDM",
    "composition": null,
    "price": "$19.90",
    "manufacturer": "3DFilamenta",
    "website": "http://3dfilamenta.com/",
    "color": null,
    "opacity": 1,
    "tags": null,
    "diameter": 1.75,
    "filament_extrusion_to_flow_multiplier": 1,
    "temp_extrude_default": 230,
    "temp_extrude_min": 200,
    "temp_extrude_max": 250,
    "bed_temp": 110,
    "min_nozzle_diameter": null,
    "extruder_fan_speed": 0,
    "bed_material": "kapton, abs slurry, acrylic, blue tape",
    "buy_now": "http://3dfilamenta.com/3dfmstore/3d-printer-consumables/39-3dfm-abs-filament-blue.html"
  },
  {
    "name": "3DFM ABS Filament- Black",
    "technology": "FDM",
    "composition": null,
    "price": "$19.90",
    "manufacturer": "3DFilamenta",
    "website": "http://3dfilamenta.com/",
    "color": null,
    "opacity": 1,
    "tags": null,
    "diameter": 1.75,
    "filament_extrusion_to_flow_multiplier": 1,
    "temp_extrude_default": 230,
    "temp_extrude_min": 200,
    "temp_extrude_max": 250,
    "bed_temp": 110,
    "min_nozzle_diameter": null,
    "extruder_fan_speed": 0,
    "bed_material": "kapton, abs slurry, acrylic, blue tape",
    "buy_now": "http://3dfilamenta.com/3dfmstore/3d-printer-consumables/40-3dfm-abs-filament-black.html"
  },
  {
    "name": "3DFM ABS Filament- Orange",
    "technology": "FDM",
    "composition": null,
    "price": "$19.90",
    "manufacturer": "3DFilamenta",
    "website": "http://3dfilamenta.com/",
    "color": null,
    "opacity": 1,
    "tags": null,
    "diameter": 1.75,
    "filament_extrusion_to_flow_multiplier": 1,
    "temp_extrude_default": 230,
    "temp_extrude_min": 200,
    "temp_extrude_max": 250,
    "bed_temp": 110,
    "min_nozzle_diameter": null,
    "extruder_fan_speed": 0,
    "bed_material": "kapton, abs slurry, acrylic, blue tape",
    "buy_now": "http://3dfilamenta.com/3dfmstore/3d-printer-consumables/41-3dfm-abs-filament-orange.html"
  },
  {
    "name": "3DFM ABS Filament- Pink",
    "technology": "FDM",
    "composition": null,
    "price": "$19.90",
    "manufacturer": "3DFilamenta",
    "website": "http://3dfilamenta.com/",
    "color": null,
    "opacity": 1,
    "tags": null,
    "diameter": 1.75,
    "filament_extrusion_to_flow_multiplier": 1,
    "temp_extrude_default": 230,
    "temp_extrude_min": 200,
    "temp_extrude_max": 250,
    "bed_temp": 110,
    "min_nozzle_diameter": null,
    "extruder_fan_speed": 0,
    "bed_material": "kapton, abs slurry, acrylic, blue tape",
    "buy_now": "http://3dfilamenta.com/3dfmstore/3d-printer-consumables/42-3dfm-abs-filament-pink.html"
  },
  {
    "name": "3DFM ABS Filament- Purple",
    "technology": "FDM",
    "composition": null,
    "price": "$19.90",
    "manufacturer": "3DFilamenta",
    "website": "http://3dfilamenta.com/",
    "color": null,
    "opacity": 1,
    "tags": null,
    "diameter": 1.75,
    "filament_extrusion_to_flow_multiplier": 1,
    "temp_extrude_default": 230,
    "temp_extrude_min": 200,
    "temp_extrude_max": 250,
    "bed_temp": 110,
    "min_nozzle_diameter": null,
    "extruder_fan_speed": 0,
    "bed_material": "kapton, abs slurry, acrylic, blue tape",
    "buy_now": "http://3dfilamenta.com/3dfmstore/3d-printer-consumables/43-3dfm-abs-filament-purple.html"
  },
  {
    "name": "3DFM ABS Filament- Red",
    "technology": "FDM",
    "composition": null,
    "price": "$19.90",
    "manufacturer": "3DFilamenta",
    "website": "http://3dfilamenta.com/",
    "color": null,
    "opacity": 1,
    "tags": null,
    "diameter": 1.75,
    "filament_extrusion_to_flow_multiplier": 1,
    "temp_extrude_default": 230,
    "temp_extrude_min": 200,
    "temp_extrude_max": 250,
    "bed_temp": 110,
    "min_nozzle_diameter": null,
    "extruder_fan_speed": 0,
    "bed_material": "kapton, abs slurry, acrylic, blue tape",
    "buy_now": "http://3dfilamenta.com/3dfmstore/3d-printer-consumables/44-3dfm-abs-filament-red.html"
  },
  {
    "name": "3DFM ABS Filament- White",
    "technology": "FDM",
    "composition": null,
    "price": "$19.90",
    "manufacturer": "3DFilamenta",
    "website": "http://3dfilamenta.com/",
    "color": null,
    "opacity": 1,
    "tags": null,
    "diameter": 1.75,
    "filament_extrusion_to_flow_multiplier": 1,
    "temp_extrude_default": 230,
    "temp_extrude_min": 200,
    "temp_extrude_max": 250,
    "bed_temp": 110,
    "min_nozzle_diameter": null,
    "extruder_fan_speed": 0,
    "bed_material": "kapton, abs slurry, acrylic, blue tape",
    "buy_now": "http://3dfilamenta.com/3dfmstore/3d-printer-consumables/45-3dfm-abs-filament-white.html"
  },
  {
    "name": "3DFM ABS Filament- Silver",
    "technology": "FDM",
    "composition": null,
    "price": "$19.90",
    "manufacturer": "3DFilamenta",
    "website": "http://3dfilamenta.com/",
    "color": null,
    "opacity": 1,
    "tags": null,
    "diameter": 1.75,
    "filament_extrusion_to_flow_multiplier": 1,
    "temp_extrude_default": 230,
    "temp_extrude_min": 200,
    "temp_extrude_max": 250,
    "bed_temp": 110,
    "min_nozzle_diameter": null,
    "extruder_fan_speed": 0,
    "bed_material": "kapton, abs slurry, acrylic, blue tape",
    "buy_now": "http://3dfilamenta.com/3dfmstore/3d-printer-consumables/46-3dfm-abs-filament-silver.html"
  },
  {
    "name": "3DFM ABS Filament- Golden",
    "technology": "FDM",
    "composition": null,
    "price": "$19.90",
    "manufacturer": "3DFilamenta",
    "website": "http://3dfilamenta.com/",
    "color": null,
    "opacity": 1,
    "tags": null,
    "diameter": 1.75,
    "filament_extrusion_to_flow_multiplier": 1,
    "temp_extrude_default": 230,
    "temp_extrude_min": 200,
    "temp_extrude_max": 250,
    "bed_temp": 110,
    "min_nozzle_diameter": null,
    "extruder_fan_speed": 0,
    "bed_material": "kapton, abs slurry, acrylic, blue tape",
    "buy_now": "http://3dfilamenta.com/3dfmstore/3d-printer-consumables/47-3dfm-abs-filament-golden.html"
  },
  {
    "name": "3DFM ABS Filament- Luminous Yellow",
    "technology": "FDM",
    "composition": null,
    "price": "$19.90",
    "manufacturer": "3DFilamenta",
    "website": "http://3dfilamenta.com/",
    "color": null,
    "opacity": 1,
    "tags": null,
    "diameter": 1.75,
    "filament_extrusion_to_flow_multiplier": 1,
    "temp_extrude_default": 230,
    "temp_extrude_min": 200,
    "temp_extrude_max": 250,
    "bed_temp": 110,
    "min_nozzle_diameter": null,
    "extruder_fan_speed": 0,
    "bed_material": "kapton, abs slurry, acrylic, blue tape",
    "buy_now": "http://3dfilamenta.com/3dfmstore/3d-printer-consumables/48-3dfm-abs-filament-luminous-yellow.html"
  },
  {
    "name": "3DFM ABS Filament- Luminous Green",
    "technology": "FDM",
    "composition": null,
    "price": "$19.90",
    "manufacturer": "3DFilamenta",
    "website": "http://3dfilamenta.com/",
    "color": null,
    "opacity": 1,
    "tags": null,
    "diameter": 1.75,
    "filament_extrusion_to_flow_multiplier": 1,
    "temp_extrude_default": 230,
    "temp_extrude_min": 200,
    "temp_extrude_max": 250,
    "bed_temp": 110,
    "min_nozzle_diameter": null,
    "extruder_fan_speed": 0,
    "bed_material": "kapton, abs slurry, acrylic, blue tape",
    "buy_now": "http://3dfilamenta.com/3dfmstore/3d-printer-consumables/49-3dfm-abs-filament-luminous-green.html"
  },
  {
    "name": "3DFM PLA Filament- Luminous Green",
    "technology": "FDM",
    "composition": null,
    "price": "$19.90",
    "manufacturer": "3DFilamenta",
    "website": "http://3dfilamenta.com/",
    "color": null,
    "opacity": 1,
    "tags": null,
    "diameter": 1.75,
    "filament_extrusion_to_flow_multiplier": 1,
    "temp_extrude_default": 200,
    "temp_extrude_min": 190,
    "temp_extrude_max": 210,
    "bed_temp": 60,
    "min_nozzle_diameter": null,
    "extruder_fan_speed": 255,
    "bed_material": "blue tape, glass, glue stick",
    "buy_now": "http://3dfilamenta.com/3dfmstore/3d-printer-consumables/50-3dfm-pla-filament-luminous-green.html"
  },
  {
    "name": "3DFM PLA Filament- Luminous Yellow",
    "technology": "FDM",
    "composition": null,
    "price": "$19.90",
    "manufacturer": "3DFilamenta",
    "website": "http://3dfilamenta.com/",
    "color": null,
    "opacity": 1,
    "tags": null,
    "diameter": 1.75,
    "filament_extrusion_to_flow_multiplier": 1,
    "temp_extrude_default": 200,
    "temp_extrude_min": 190,
    "temp_extrude_max": 210,
    "bed_temp": 60,
    "min_nozzle_diameter": null,
    "extruder_fan_speed": 255,
    "bed_material": "blue tape, glass, glue stick",
    "buy_now": "http://3dfilamenta.com/3dfmstore/3d-printer-consumables/51-3dfm-pla-filament-luminous-yellow.html"
  },
  {
    "name": "3DFM PLA Filament- Fluorescent Orange",
    "technology": "FDM",
    "composition": null,
    "price": "$19.90",
    "manufacturer": "3DFilamenta",
    "website": "http://3dfilamenta.com/",
    "color": null,
    "opacity": 1,
    "tags": null,
    "diameter": 1.75,
    "filament_extrusion_to_flow_multiplier": 1,
    "temp_extrude_default": 200,
    "temp_extrude_min": 190,
    "temp_extrude_max": 210,
    "bed_temp": 60,
    "min_nozzle_diameter": null,
    "extruder_fan_speed": 255,
    "bed_material": "blue tape, glass, glue stick",
    "buy_now": "http://3dfilamenta.com/3dfmstore/3d-printer-consumables/52-3dfm-pla-filament-flouroscent-orange.html"
  },
  {
    "name": "3DFM PLA Filament- Fluorescent Red",
    "technology": "FDM",
    "composition": null,
    "price": "$19.90",
    "manufacturer": "3DFilamenta",
    "website": "http://3dfilamenta.com/",
    "color": null,
    "opacity": 1,
    "tags": null,
    "diameter": 1.75,
    "filament_extrusion_to_flow_multiplier": 1,
    "temp_extrude_default": 200,
    "temp_extrude_min": 190,
    "temp_extrude_max": 210,
    "bed_temp": 60,
    "min_nozzle_diameter": null,
    "extruder_fan_speed": 255,
    "bed_material": "blue tape, glass, glue stick",
    "buy_now": "http://3dfilamenta.com/3dfmstore/3d-printer-consumables/53-3dfm-pla-filament-flouroscent-red.html"
  },
  {
    "name": "3DFM PLA Filament- Fluorescent Yellow",
    "technology": "FDM",
    "composition": null,
    "price": "$19.90",
    "manufacturer": "3DFilamenta",
    "website": "http://3dfilamenta.com/",
    "color": null,
    "opacity": 1,
    "tags": null,
    "diameter": 1.75,
    "filament_extrusion_to_flow_multiplier": 1,
    "temp_extrude_default": 200,
    "temp_extrude_min": 190,
    "temp_extrude_max": 210,
    "bed_temp": 60,
    "min_nozzle_diameter": null,
    "extruder_fan_speed": 255,
    "bed_material": "blue tape, glass, glue stick",
    "buy_now": "http://3dfilamenta.com/3dfmstore/3d-printer-consumables/54-3dfm-pla-filament-flouroscent-yellow.html"
  },
  {
    "name": "3DFM PLA Filament-Yellow",
    "technology": "FDM",
    "composition": null,
    "price": "$19.90",
    "manufacturer": "3DFilamenta",
    "website": "http://3dfilamenta.com/",
    "color": null,
    "opacity": 1,
    "tags": null,
    "diameter": 1.75,
    "filament_extrusion_to_flow_multiplier": 1,
    "temp_extrude_default": 200,
    "temp_extrude_min": 190,
    "temp_extrude_max": 210,
    "bed_temp": 60,
    "min_nozzle_diameter": null,
    "extruder_fan_speed": 255,
    "bed_material": "blue tape, glass, glue stick",
    "buy_now": "http://3dfilamenta.com/3dfmstore/3d-printer-consumables/55-3dfm-pla-filament-yellow.html"
  },
  {
    "name": "3DFM PLA Filament-Orange",
    "technology": "FDM",
    "composition": null,
    "price": "$21.00",
    "manufacturer": "3DFilamenta",
    "website": "http://3dfilamenta.com/",
    "color": null,
    "opacity": 1,
    "tags": null,
    "diameter": 1.75,
    "filament_extrusion_to_flow_multiplier": 1,
    "temp_extrude_default": 200,
    "temp_extrude_min": 190,
    "temp_extrude_max": 210,
    "bed_temp": 60,
    "min_nozzle_diameter": null,
    "extruder_fan_speed": 255,
    "bed_material": "blue tape, glass, glue stick",
    "buy_now": "http://3dfilamenta.com/3dfmstore/3d-printer-consumables/56-3dfm-pla-filament-orange.html"
  },
  {
    "name": "3DFM PLA Filament-Red",
    "technology": "FDM",
    "composition": null,
    "price": "$21.00",
    "manufacturer": "3DFilamenta",
    "website": "http://3dfilamenta.com/",
    "color": null,
    "opacity": 1,
    "tags": null,
    "diameter": 1.75,
    "filament_extrusion_to_flow_multiplier": 1,
    "temp_extrude_default": 200,
    "temp_extrude_min": 190,
    "temp_extrude_max": 210,
    "bed_temp": 60,
    "min_nozzle_diameter": null,
    "extruder_fan_speed": 255,
    "bed_material": "blue tape, glass, glue stick",
    "buy_now": "http://3dfilamenta.com/3dfmstore/3d-printer-consumables/57-3dfm-pla-filament-red.html"
  },
  {
    "name": "3DFM PLA Filament-Blue",
    "technology": "FDM",
    "composition": null,
    "price": "$21.00",
    "manufacturer": "3DFilamenta",
    "website": "http://3dfilamenta.com/",
    "color": null,
    "opacity": 1,
    "tags": null,
    "diameter": 1.75,
    "filament_extrusion_to_flow_multiplier": 1,
    "temp_extrude_default": 200,
    "temp_extrude_min": 190,
    "temp_extrude_max": 210,
    "bed_temp": 60,
    "min_nozzle_diameter": null,
    "extruder_fan_speed": 255,
    "bed_material": "blue tape, glass, glue stick",
    "buy_now": "http://3dfilamenta.com/3dfmstore/3d-printer-consumables/58-3dfm-pla-filament-blue.html"
  },
  {
    "name": "3DFM PLA Filament-Black",
    "technology": "FDM",
    "composition": null,
    "price": "$21.00",
    "manufacturer": "3DFilamenta",
    "website": "http://3dfilamenta.com/",
    "color": null,
    "opacity": 1,
    "tags": null,
    "diameter": 1.75,
    "filament_extrusion_to_flow_multiplier": 1,
    "temp_extrude_default": 200,
    "temp_extrude_min": 190,
    "temp_extrude_max": 210,
    "bed_temp": 60,
    "min_nozzle_diameter": null,
    "extruder_fan_speed": 255,
    "bed_material": "blue tape, glass, glue stick",
    "buy_now": "http://3dfilamenta.com/3dfmstore/3d-printer-consumables/59-3dfm-pla-filament-black.html"
  },
  {
    "name": "3DFM PLA Filament-White",
    "technology": "FDM",
    "composition": null,
    "price": "$23.90",
    "manufacturer": "3DFilamenta",
    "website": "http://3dfilamenta.com/",
    "color": null,
    "opacity": 1,
    "tags": null,
    "diameter": 1.75,
    "filament_extrusion_to_flow_multiplier": 1,
    "temp_extrude_default": 200,
    "temp_extrude_min": 190,
    "temp_extrude_max": 210,
    "bed_temp": 60,
    "min_nozzle_diameter": null,
    "extruder_fan_speed": 255,
    "bed_material": "blue tape, glass, glue stick",
    "buy_now": "http://3dfilamenta.com/3dfmstore/3d-printer-consumables/60-3dfm-pla-filament-white.html"
  },
  {
    "name": "3DFM PLA Filament-Natural",
    "technology": "FDM",
    "composition": null,
    "price": "$23.90",
    "manufacturer": "3DFilamenta",
    "website": "http://3dfilamenta.com/",
    "color": null,
    "opacity": 1,
    "tags": null,
    "diameter": 1.75,
    "filament_extrusion_to_flow_multiplier": 1,
    "temp_extrude_default": 200,
    "temp_extrude_min": 190,
    "temp_extrude_max": 210,
    "bed_temp": 60,
    "min_nozzle_diameter": null,
    "extruder_fan_speed": 255,
    "bed_material": "blue tape, glass, glue stick",
    "buy_now": "http://3dfilamenta.com/3dfmstore/3d-printer-consumables/61-3dfm-pla-filament-natural.html"
  },
  {
    "name": "3DFM PLA Filament-Green",
    "technology": "FDM",
    "composition": null,
    "price": "$23.90",
    "manufacturer": "3DFilamenta",
    "website": "http://3dfilamenta.com/",
    "color": null,
    "opacity": 1,
    "tags": null,
    "diameter": 1.75,
    "filament_extrusion_to_flow_multiplier": 1,
    "temp_extrude_default": 200,
    "temp_extrude_min": 190,
    "temp_extrude_max": 210,
    "bed_temp": 60,
    "min_nozzle_diameter": null,
    "extruder_fan_speed": 255,
    "bed_material": "blue tape, glass, glue stick",
    "buy_now": "http://3dfilamenta.com/3dfmstore/3d-printer-consumables/62-3dfm-pla-filament-green.html"
  },
  {
    "name": "3DFM PLA Filament-Pink",
    "technology": "FDM",
    "composition": null,
    "price": "$23.90",
    "manufacturer": "3DFilamenta",
    "website": "http://3dfilamenta.com/",
    "color": null,
    "opacity": 1,
    "tags": null,
    "diameter": 1.75,
    "filament_extrusion_to_flow_multiplier": 1,
    "temp_extrude_default": 200,
    "temp_extrude_min": 190,
    "temp_extrude_max": 210,
    "bed_temp": 60,
    "min_nozzle_diameter": null,
    "extruder_fan_speed": 255,
    "bed_material": "blue tape, glass, glue stick",
    "buy_now": "http://3dfilamenta.com/3dfmstore/3d-printer-consumables/63-3dfm-pla-filament-pink.html"
  },
  {
    "name": "3DFM PLA Filament-Purple",
    "technology": "FDM",
    "composition": null,
    "price": "$23.90",
    "manufacturer": "3DFilamenta",
    "website": "http://3dfilamenta.com/",
    "color": null,
    "opacity": 1,
    "tags": null,
    "diameter": 1.75,
    "filament_extrusion_to_flow_multiplier": 1,
    "temp_extrude_default": 200,
    "temp_extrude_min": 190,
    "temp_extrude_max": 210,
    "bed_temp": 60,
    "min_nozzle_diameter": null,
    "extruder_fan_speed": 255,
    "bed_material": "blue tape, glass, glue stick",
    "buy_now": "http://3dfilamenta.com/3dfmstore/3d-printer-consumables/64-3dfm-pla-filament-purple.html"
  },
  {
    "name": "3DFM PLA Filament-Silver",
    "technology": "FDM",
    "composition": null,
    "price": "$23.90",
    "manufacturer": "3DFilamenta",
    "website": "http://3dfilamenta.com/",
    "color": null,
    "opacity": 1,
    "tags": null,
    "diameter": 1.75,
    "filament_extrusion_to_flow_multiplier": 1,
    "temp_extrude_default": 200,
    "temp_extrude_min": 190,
    "temp_extrude_max": 210,
    "bed_temp": 60,
    "min_nozzle_diameter": null,
    "extruder_fan_speed": 255,
    "bed_material": "blue tape, glass, glue stick",
    "buy_now": "http://3dfilamenta.com/3dfmstore/3d-printer-consumables/65-3dfm-pla-filament-silver.html"
  },
  {
    "name": "3DFM PLA Filament-Golden",
    "technology": "FDM",
    "composition": null,
    "price": "$23.90",
    "manufacturer": "3DFilamenta",
    "website": "http://3dfilamenta.com/",
    "color": null,
    "opacity": 1,
    "tags": null,
    "diameter": 1.75,
    "filament_extrusion_to_flow_multiplier": 1,
    "temp_extrude_default": 200,
    "temp_extrude_min": 190,
    "temp_extrude_max": 210,
    "bed_temp": 60,
    "min_nozzle_diameter": null,
    "extruder_fan_speed": 255,
    "bed_material": "blue tape, glass, glue stick",
    "buy_now": "http://3dfilamenta.com/3dfmstore/3d-printer-consumables/66-3dfm-pla-filament-golden.html"
  },
  {
    "name": "3DFM NYLON Filament ",
    "technology": "FDM",
    "composition": null,
    "price": "$23.90",
    "manufacturer": "3DFilamenta",
    "website": "http://3dfilamenta.com/",
    "color": null,
    "opacity": 1,
    "tags": null,
    "diameter": 1.75,
    "filament_extrusion_to_flow_multiplier": 1,
    "temp_extrude_default": 200,
    "temp_extrude_min": 190,
    "temp_extrude_max": 210,
    "bed_temp": 60,
    "min_nozzle_diameter": null,
    "extruder_fan_speed": 255,
    "bed_material": "blue tape, glass, glue stick",
    "buy_now": "http://3dfilamenta.com/3dfmstore/nylon-filament/67-3dfm-nylon-filament.html"
  },
  {
    "name": "3DFM PVA Filament ",
    "technology": "FDM",
    "composition": null,
    "price": "$23.90",
    "manufacturer": "3DFilamenta",
    "website": "http://3dfilamenta.com/",
    "color": null,
    "opacity": 1,
    "tags": null,
    "diameter": 1.75,
    "filament_extrusion_to_flow_multiplier": 1,
    "temp_extrude_default": 200,
    "temp_extrude_min": 190,
    "temp_extrude_max": 210,
    "bed_temp": 60,
    "min_nozzle_diameter": null,
    "extruder_fan_speed": 255,
    "bed_material": "blue tape, glass, glue stick",
    "buy_now": "http://3dfilamenta.com/3dfmstore/3d-printer-consumables/68-3dfm-pva-filament.html"
  },
  {
    "name": "3DFM POM Filament ",
    "technology": "FDM",
    "composition": null,
    "price": "$23.90",
    "manufacturer": "3DFilamenta",
    "website": "http://3dfilamenta.com/",
    "color": null,
    "opacity": 1,
    "tags": null,
    "diameter": 1.75,
    "filament_extrusion_to_flow_multiplier": 1,
    "temp_extrude_default": 200,
    "temp_extrude_min": 190,
    "temp_extrude_max": 210,
    "bed_temp": 60,
    "min_nozzle_diameter": null,
    "extruder_fan_speed": 255,
    "bed_material": "blue tape, glass, glue stick",
    "buy_now": "http://3dfilamenta.com/3dfmstore/3d-printer-consumables/69-3dfm-pom-filament.html"
  },
  {
    "name": "3DFM PC Filament ",
    "technology": "FDM",
    "composition": null,
    "price": "$23.90",
    "manufacturer": "3DFilamenta",
    "website": "http://3dfilamenta.com/",
    "color": null,
    "opacity": 1,
    "tags": null,
    "diameter": 1.75,
    "filament_extrusion_to_flow_multiplier": 1,
    "temp_extrude_default": 200,
    "temp_extrude_min": 190,
    "temp_extrude_max": 210,
    "bed_temp": 60,
    "min_nozzle_diameter": null,
    "extruder_fan_speed": 255,
    "bed_material": "blue tape, glass, glue stick",
    "buy_now": "http://3dfilamenta.com/3dfmstore/3d-printer-consumables/70-3dfm-pc-filament.html"
  },
  {
    "name": "3DFM HIPS Filament ",
    "technology": "FDM",
    "composition": null,
    "price": "$23.90",
    "manufacturer": "3DFilamenta",
    "website": "http://3dfilamenta.com/",
    "color": null,
    "opacity": 1,
    "tags": null,
    "diameter": 1.75,
    "filament_extrusion_to_flow_multiplier": 1,
    "temp_extrude_default": 200,
    "temp_extrude_min": 190,
    "temp_extrude_max": 210,
    "bed_temp": 60,
    "min_nozzle_diameter": null,
    "extruder_fan_speed": 255,
    "bed_material": "blue tape, glass, glue stick",
    "buy_now": "http://3dfilamenta.com/3dfmstore/3d-printer-consumables/71-3dfm-hips-filament.html"
  },
  {
    "name": "3DFM PETG Filament ",
    "technology": "FDM",
    "composition": null,
    "price": "$23.90",
    "manufacturer": "3DFilamenta",
    "website": "http://3dfilamenta.com/",
    "color": null,
    "opacity": 1,
    "tags": null,
    "diameter": 1.75,
    "filament_extrusion_to_flow_multiplier": 1,
    "temp_extrude_default": 200,
    "temp_extrude_min": 190,
    "temp_extrude_max": 210,
    "bed_temp": 60,
    "min_nozzle_diameter": null,
    "extruder_fan_speed": 255,
    "bed_material": "blue tape, glass, glue stick",
    "buy_now": "http://3dfilamenta.com/3dfmstore/3d-printer-consumables/72-3dfm-petg-filament.html"
  },
  {
    "name": "3DFM Rubber Flex Filament ",
    "technology": "FDM",
    "composition": null,
    "price": "$23.90",
    "manufacturer": "3DFilamenta",
    "website": "http://3dfilamenta.com/",
    "color": null,
    "opacity": 1,
    "tags": null,
    "diameter": 1.75,
    "filament_extrusion_to_flow_multiplier": 1,
    "temp_extrude_default": 200,
    "temp_extrude_min": 190,
    "temp_extrude_max": 210,
    "bed_temp": 60,
    "min_nozzle_diameter": null,
    "extruder_fan_speed": 255,
    "bed_material": "blue tape, glass, glue stick",
    "buy_now": "http://3dfilamenta.com/3dfmstore/3d-printer-consumables/73-3dfm-rubber-flex-filament.html"
  },
  {
    "name": "3DFM Woodfill Filament ",
    "technology": "FDM",
    "composition": null,
    "price": "$19.90",
    "manufacturer": "3DFilamenta",
    "website": "http://3dfilamenta.com/",
    "color": null,
    "opacity": 1,
    "tags": null,
    "diameter": 1.75,
    "filament_extrusion_to_flow_multiplier": 1,
    "temp_extrude_default": 200,
    "temp_extrude_min": 190,
    "temp_extrude_max": 210,
    "bed_temp": 60,
    "min_nozzle_diameter": null,
    "extruder_fan_speed": 255,
    "bed_material": "blue tape, glass, glue stick",
    "buy_now": "http://3dfilamenta.com/3dfmstore/3d-printer-consumables/74-3dfm-woodfill-filament.html"
  },
  {
    "name": "3DFM PP Filament ",
    "technology": "FDM",
    "composition": null,
    "price": "$19.90",
    "manufacturer": "3DFilamenta",
    "website": "http://3dfilamenta.com/",
    "color": null,
    "opacity": 1,
    "tags": null,
    "diameter": 1.75,
    "filament_extrusion_to_flow_multiplier": 1,
    "temp_extrude_default": 200,
    "temp_extrude_min": 190,
    "temp_extrude_max": 210,
    "bed_temp": 60,
    "min_nozzle_diameter": null,
    "extruder_fan_speed": 255,
    "bed_material": "blue tape, glass, glue stick",
    "buy_now": "http://3dfilamenta.com/3dfmstore/3d-printer-consumables/75-3dfm-pp-filament.html"
  }
]